<annotation>
	<folder></folder>
	<filename>ManilaBay_575e4e2b7_jpg.rf.245dc81f9e2cd0fece90e815f32d9dbf.jpg</filename>
	<path>ManilaBay_575e4e2b7_jpg.rf.245dc81f9e2cd0fece90e815f32d9dbf.jpg</path>
	<source>
		<database>roboflow.com</database>
	</source>
	<size>
		<width>640</width>
		<height>640</height>
		<depth>3</depth>
	</size>
	<segmented>0</segmented>
	<object>
		<name>plastic_waste</name>
		<pose>Unspecified</pose>
		<truncated>0</truncated>
		<difficult>0</difficult>
		<occluded>0</occluded>
		<bndbox>
			<xmin>131</xmin>
			<xmax>223</xmax>
			<ymin>279</ymin>
			<ymax>411</ymax>
		</bndbox>
	</object>
	<object>
		<name>styrofoam_waste</name>
		<pose>Unspecified</pose>
		<truncated>0</truncated>
		<difficult>0</difficult>
		<occluded>0</occluded>
		<bndbox>
			<xmin>396</xmin>
			<xmax>472</xmax>
			<ymin>175</ymin>
			<ymax>307</ymax>
		</bndbox>
	</object>
</annotation>
