<annotation>
	<folder></folder>
	<filename>ManilaBay_dc8a8ec3fd_jpg.rf.f6badaa82ef0f85a3fcb2ffc43cf8ea6.jpg</filename>
	<path>ManilaBay_dc8a8ec3fd_jpg.rf.f6badaa82ef0f85a3fcb2ffc43cf8ea6.jpg</path>
	<source>
		<database>roboflow.com</database>
	</source>
	<size>
		<width>640</width>
		<height>640</height>
		<depth>3</depth>
	</size>
	<segmented>0</segmented>
	<object>
		<name>plastic_waste</name>
		<pose>Unspecified</pose>
		<truncated>0</truncated>
		<difficult>0</difficult>
		<occluded>0</occluded>
		<bndbox>
			<xmin>478</xmin>
			<xmax>598</xmax>
			<ymin>359</ymin>
			<ymax>449</ymax>
		</bndbox>
	</object>
	<object>
		<name>plastic_waste</name>
		<pose>Unspecified</pose>
		<truncated>0</truncated>
		<difficult>0</difficult>
		<occluded>0</occluded>
		<bndbox>
			<xmin>183</xmin>
			<xmax>249</xmax>
			<ymin>339</ymin>
			<ymax>411</ymax>
		</bndbox>
	</object>
</annotation>
