<annotation>
	<folder></folder>
	<filename>ManilaBay_f05bf6910_jpg.rf.ce24897325ae7feead6c112d6c478353.jpg</filename>
	<path>ManilaBay_f05bf6910_jpg.rf.ce24897325ae7feead6c112d6c478353.jpg</path>
	<source>
		<database>roboflow.com</database>
	</source>
	<size>
		<width>640</width>
		<height>640</height>
		<depth>3</depth>
	</size>
	<segmented>0</segmented>
	<object>
		<name>plastic_waste</name>
		<pose>Unspecified</pose>
		<truncated>0</truncated>
		<difficult>0</difficult>
		<occluded>0</occluded>
		<bndbox>
			<xmin>114</xmin>
			<xmax>558</xmax>
			<ymin>43</ymin>
			<ymax>315</ymax>
		</bndbox>
	</object>
</annotation>
